bolna/__init__.py
bolna/assistant.py
bolna/constants.py
bolna/models.py
bolna/prompts.py
bolna/providers.py
bolna/agent_manager/__init__.py
bolna/agent_manager/assistant_manager.py
bolna/agent_manager/base_manager.py
bolna/agent_manager/task_manager.py
bolna/agent_types/__init__.py
bolna/agent_types/base_agent.py
bolna/agent_types/contextual_conversational_agent.py
bolna/agent_types/extraction_agent.py
bolna/agent_types/graph_agent.py
bolna/agent_types/graph_based_conversational_agent.py
bolna/agent_types/knowledgebase_agent.py
bolna/agent_types/summarization_agent.py
bolna/agent_types/webhook_agent.py
bolna/classification/classification.py
bolna/classification/deberta.py
bolna/helpers/__init__.py
bolna/helpers/analytics_helpers.py
bolna/helpers/cache_helpers.py
bolna/helpers/function_calling_helpers.py
bolna/helpers/logger_config.py
bolna/helpers/mark_event_meta_data.py
bolna/helpers/observable_variable.py
bolna/helpers/rag_service_client.py
bolna/helpers/utils.py
bolna/helpers/vad.py
bolna/input_handlers/__init__.py
bolna/input_handlers/default.py
bolna/input_handlers/telephony.py
bolna/input_handlers/telephony_providers/exotel.py
bolna/input_handlers/telephony_providers/plivo.py
bolna/input_handlers/telephony_providers/twilio.py
bolna/llms/__init__.py
bolna/llms/azure_llm.py
bolna/llms/litellm.py
bolna/llms/llm.py
bolna/llms/openai_llm.py
bolna/memory/cache/__init__.py
bolna/memory/cache/base_cache.py
bolna/memory/cache/inmemory_scalar_cache.py
bolna/memory/cache/vector_cache.py
bolna/output_handlers/__init__.py
bolna/output_handlers/default.py
bolna/output_handlers/telephony.py
bolna/output_handlers/telephony_providers/exotel.py
bolna/output_handlers/telephony_providers/plivo.py
bolna/output_handlers/telephony_providers/twilio.py
bolna/synthesizer/__init__.py
bolna/synthesizer/azure_synthesizer.py
bolna/synthesizer/base_synthesizer.py
bolna/synthesizer/cartesia_synthesizer.py
bolna/synthesizer/deepgram_synthesizer.py
bolna/synthesizer/elevenlabs_synthesizer.py
bolna-0.10.0.dist-info/licenses/LICENSE
bolna-0.10.0.dist-info/METADATA
bolna-0.10.0.dist-info/WHEEL
bolna-0.10.0.dist-info/top_level.txt
bolna-0.10.0.dist-info/RECORD
