Metadata-Version: 2.4
Name: bolna
Version: 0.10.0
Author-email: Prateek Sachan <ps@prateeksachan.com>
License: Copyright (c) 2023 Bolna
Classifier: License :: OSI Approved :: MIT License
Classifier: Programming Language :: Python
Classifier: Programming Language :: Python :: 3
Requires-Python: >=3.8
License-File: LICENSE
Requires-Dist: aiobotocore==2.9.0
Requires-Dist: aiofiles==23.2.1
Requires-Dist: aiohttp==3.9.1
Requires-Dist: azure-cognitiveservices-speech==1.38.0
Requires-Dist: google-cloud-speech==2.25.0
Requires-Dist: fastapi==0.108.0
Requires-Dist: fastembed==0.3.5
Requires-Dist: huggingface-hub==0.24.3
Requires-Dist: litellm==1.65.0
Requires-Dist: llama_index==0.10.65
Requires-Dist: llama-index-vector-stores-lancedb==0.1.7
Requires-Dist: numpy==1.26.1
Requires-Dist: openai>=1.10.0
Requires-Dist: plivo==4.47.0
Requires-Dist: pydantic==2.5.3
Requires-Dist: pydub==0.25.1
Requires-Dist: pymongo==4.8.0
Requires-Dist: python-dateutil==2.8.2
Requires-Dist: python-dotenv==1.0.0
Requires-Dist: redis==5.0.1
Requires-Dist: requests==2.31.0
Requires-Dist: tiktoken>=0.6.0
Requires-Dist: torchaudio==2.0.1
Requires-Dist: twilio==8.9.0
Requires-Dist: uvicorn==0.22.0
Requires-Dist: websockets==15.0.1
Requires-Dist: onnxruntime>=1.16.3
Requires-Dist: scipy==1.11.4
Requires-Dist: semantic-router==0.0.46
Requires-Dist: sentence-transformers==3.0.1
Requires-Dist: tokenizers==0.15.2
Requires-Dist: optimum[onnxruntime]
Requires-Dist: lancedb==0.12.0
Requires-Dist: pymongo==4.8.0
Requires-Dist: httpx[http2]>=0.25.0
Provides-Extra: dev
Requires-Dist: pip-tools; extra == "dev"
Dynamic: license-file
